{
  "fetched_at": "2026-04-11T03:07:22.643332+00:00",
  "source": "Akron / Summit County, Ohio",
  "category": "foreclosure",
  "description": "Active foreclosure/lis pendens",
  "total": 7,
  "records": [
    {
      "doc_num": "STEVENS 04",
      "doc_type": "NOFC",
      "filed": "2026-04-10",
      "cat": "NOFC",
      "cat_label": "Pre-foreclosure",
      "owner": "Jacqueline Stevens",
      "grantee": "The Huntington National Bank",
      "amount": null,
      "legal": "THE HUNTINGTON NATIONAL BANK -VS- JACQUELINE STEVENS",
      "prop_address": "23 CHURCH ST",
      "prop_city": "HUDSON",
      "prop_state": "OH",
      "prop_zip": "44236",
      "mail_address": "23 CHURCH ST",
      "mail_city": "Hudson",
      "mail_state": "OH",
      "mail_zip": "44236",
      "clerk_url": "https://newcivilfilings.summitoh.net/",
      "flags": [
        "Pre-foreclosure",
        "New this week"
      ],
      "score": 63,
      "match_method": "last_name_unique_fallback",
      "match_score": 0.82,
      "with_address": 1,
      "distress_sources": [
        "foreclosure"
      ],
      "distress_count": 1,
      "hot_stack": false,
      "luc": "510",
      "acres": ".1500",
      "is_vacant_land": false,
      "is_vacant_home": false,
      "is_absentee": false,
      "is_out_of_state": false,
      "phones": [],
      "phone_types": [],
      "emails": [],
      "skip_trace_source": "",
      "parcel_id": "3200244",
      "assessed_value": null,
      "estimated_value": null,
      "last_sale_price": null,
      "last_sale_year": null,
      "est_mortgage_balance": null,
      "est_equity": null,
      "est_arrears": null,
      "est_payoff": null,
      "subject_to_score": 25,
      "mortgage_signals": [
        "Active foreclosure"
      ]
    },
    {
      "doc_num": "BYE 04",
      "doc_type": "NOFC",
      "filed": "2026-04-10",
      "cat": "NOFC",
      "cat_label": "Pre-foreclosure",
      "owner": "Tracy Bye",
      "grantee": "Kristen M. Scalise",
      "amount": null,
      "legal": "KRISTEN M. SCALISE -VS- UNKNOWN HEIRS OF TRACY BYE",
      "prop_address": "1363 CARNEGIE AVE",
      "prop_city": "AKRON",
      "prop_state": "OH",
      "prop_zip": "44314",
      "mail_address": "1363 CARNEGIE AVE",
      "mail_city": "Akron",
      "mail_state": "OH",
      "mail_zip": "44314",
      "clerk_url": "https://newcivilfilings.summitoh.net/",
      "flags": [
        "Pre-foreclosure",
        "New this week"
      ],
      "score": 63,
      "match_method": "exact_name_variant",
      "match_score": 1.0,
      "with_address": 1,
      "distress_sources": [
        "foreclosure"
      ],
      "distress_count": 1,
      "hot_stack": false,
      "luc": "510",
      "acres": "",
      "is_vacant_land": false,
      "is_vacant_home": false,
      "is_absentee": false,
      "is_out_of_state": false,
      "phones": [],
      "phone_types": [],
      "emails": [],
      "skip_trace_source": "",
      "parcel_id": "6827502",
      "assessed_value": null,
      "estimated_value": null,
      "last_sale_price": null,
      "last_sale_year": null,
      "est_mortgage_balance": null,
      "est_equity": null,
      "est_arrears": null,
      "est_payoff": null,
      "subject_to_score": 25,
      "mortgage_signals": [
        "Active foreclosure"
      ]
    },
    {
      "doc_num": "BLAKE 04",
      "doc_type": "NOFC",
      "filed": "2026-04-10",
      "cat": "NOFC",
      "cat_label": "Pre-foreclosure",
      "owner": "Joseph L. Blake",
      "grantee": "Kristen M. Scalise",
      "amount": null,
      "legal": "KRISTEN M. SCALISE -VS- UNKNOWN HEIRS OF JOSEPH L. BLAKE",
      "prop_address": "770 SILVERCREST AVE",
      "prop_city": "AKRON",
      "prop_state": "OH",
      "prop_zip": "44314",
      "mail_address": "770 SILVERCREST AVE",
      "mail_city": "Akron",
      "mail_state": "OH",
      "mail_zip": "44314",
      "clerk_url": "https://newcivilfilings.summitoh.net/",
      "flags": [
        "Pre-foreclosure",
        "New this week"
      ],
      "score": 63,
      "match_method": "exact_name_variant",
      "match_score": 1.0,
      "with_address": 1,
      "distress_sources": [
        "foreclosure"
      ],
      "distress_count": 1,
      "hot_stack": false,
      "luc": "510",
      "acres": "",
      "is_vacant_land": false,
      "is_vacant_home": false,
      "is_absentee": false,
      "is_out_of_state": false,
      "phones": [],
      "phone_types": [],
      "emails": [],
      "skip_trace_source": "",
      "parcel_id": "6708475",
      "assessed_value": null,
      "estimated_value": null,
      "last_sale_price": null,
      "last_sale_year": null,
      "est_mortgage_balance": null,
      "est_equity": null,
      "est_arrears": null,
      "est_payoff": null,
      "subject_to_score": 25,
      "mortgage_signals": [
        "Active foreclosure"
      ]
    },
    {
      "doc_num": "PCF1-T1-R74",
      "doc_type": "NOFC",
      "filed": "2026-04-09",
      "cat": "NOFC",
      "cat_label": "Pre-foreclosure",
      "owner": "Demetrius Marquel Lash",
      "grantee": "Us Bank National Association",
      "amount": null,
      "legal": "US BANK NATIONAL ASSOCIATION -VS- DEMETRIUS MARQUEL LASH AKA DEMETRIUS M L",
      "prop_address": "76 E IDO AVE",
      "prop_city": "AKRON",
      "prop_state": "OH",
      "prop_zip": "44301",
      "mail_address": "76 E IDO AVE",
      "mail_city": "Akron",
      "mail_state": "OH",
      "mail_zip": "44301",
      "clerk_url": "https://newcivilfilings.summitoh.net/",
      "flags": [
        "Pre-foreclosure",
        "New this week"
      ],
      "score": 63,
      "match_method": "exact_name_variant",
      "match_score": 1.0,
      "with_address": 1,
      "distress_sources": [
        "foreclosure"
      ],
      "distress_count": 1,
      "hot_stack": false,
      "luc": "510",
      "acres": "",
      "is_vacant_land": false,
      "is_vacant_home": false,
      "is_absentee": false,
      "is_out_of_state": false,
      "phones": [],
      "phone_types": [],
      "emails": [],
      "skip_trace_source": "",
      "parcel_id": "6729080",
      "assessed_value": null,
      "estimated_value": null,
      "last_sale_price": null,
      "last_sale_year": null,
      "est_mortgage_balance": null,
      "est_equity": null,
      "est_arrears": null,
      "est_payoff": null,
      "subject_to_score": 25,
      "mortgage_signals": [
        "Active foreclosure"
      ]
    },
    {
      "doc_num": "NANASSY 04",
      "doc_type": "NOFC",
      "filed": "2026-04-09",
      "cat": "NOFC",
      "cat_label": "Pre-foreclosure",
      "owner": "Debra Nanassy",
      "grantee": "Lakeview Loan Servicing Llc",
      "amount": null,
      "legal": "LAKEVIEW LOAN SERVICING LLC -VS- DEBRA NANASSY",
      "prop_address": "38 BERWYCK DR",
      "prop_city": "AKRON",
      "prop_state": "OH",
      "prop_zip": "44312",
      "mail_address": "38 BERWYCK DR",
      "mail_city": "Akron",
      "mail_state": "OH",
      "mail_zip": "44312",
      "clerk_url": "https://newcivilfilings.summitoh.net/",
      "flags": [
        "Pre-foreclosure",
        "New this week"
      ],
      "score": 63,
      "match_method": "exact_name_variant",
      "match_score": 1.0,
      "with_address": 1,
      "distress_sources": [
        "foreclosure"
      ],
      "distress_count": 1,
      "hot_stack": false,
      "luc": "510",
      "acres": ".1800",
      "is_vacant_land": false,
      "is_vacant_home": false,
      "is_absentee": false,
      "is_out_of_state": false,
      "phones": [],
      "phone_types": [],
      "emails": [],
      "skip_trace_source": "",
      "parcel_id": "6836635",
      "assessed_value": null,
      "estimated_value": null,
      "last_sale_price": null,
      "last_sale_year": null,
      "est_mortgage_balance": null,
      "est_equity": null,
      "est_arrears": null,
      "est_payoff": null,
      "subject_to_score": 25,
      "mortgage_signals": [
        "Active foreclosure"
      ]
    },
    {
      "doc_num": "LAWRENCE 04",
      "doc_type": "NOFC",
      "filed": "2026-04-10",
      "cat": "NOFC",
      "cat_label": "Pre-foreclosure",
      "owner": "Rena Lawrence",
      "grantee": "Pnc Bank National Association",
      "amount": null,
      "legal": "PNC BANK NATIONAL ASSOCIATION -VS- UNKNOWN HEIRS OF RENA LAWRENCE",
      "prop_address": "",
      "prop_city": "",
      "prop_state": "OH",
      "prop_zip": "",
      "mail_address": "",
      "mail_city": "",
      "mail_state": "",
      "mail_zip": "",
      "clerk_url": "https://newcivilfilings.summitoh.net/",
      "flags": [
        "Pre-foreclosure",
        "New this week",
        "No property match"
      ],
      "score": 55,
      "match_method": "no_property_match",
      "match_score": 0.0,
      "with_address": 0,
      "distress_sources": [
        "foreclosure"
      ],
      "distress_count": 1,
      "hot_stack": false,
      "luc": "",
      "acres": "",
      "is_vacant_land": false,
      "is_vacant_home": false,
      "is_absentee": false,
      "is_out_of_state": false,
      "phones": [],
      "phone_types": [],
      "emails": [],
      "skip_trace_source": "",
      "parcel_id": "",
      "assessed_value": null,
      "estimated_value": null,
      "last_sale_price": null,
      "last_sale_year": null,
      "est_mortgage_balance": null,
      "est_equity": null,
      "est_arrears": null,
      "est_payoff": null,
      "subject_to_score": 25,
      "mortgage_signals": [
        "Active foreclosure"
      ]
    },
    {
      "doc_num": "FIDUC 04",
      "doc_type": "NOFC",
      "filed": "2026-04-09",
      "cat": "NOFC",
      "cat_label": "Pre-foreclosure",
      "owner": "Or Fiduc",
      "grantee": "Towd Point Mortgage Trust 2019-3, U.S. B",
      "amount": null,
      "legal": "TOWD POINT MORTGAGE TRUST 2019-3, U.S. B -VS- UNKNOWN ADMINISTRATOR, EXECUTOR OR FIDUC",
      "prop_address": "",
      "prop_city": "",
      "prop_state": "OH",
      "prop_zip": "",
      "mail_address": "",
      "mail_city": "",
      "mail_state": "",
      "mail_zip": "",
      "clerk_url": "https://newcivilfilings.summitoh.net/",
      "flags": [
        "Pre-foreclosure",
        "New this week"
      ],
      "score": 55,
      "match_method": "unmatched",
      "match_score": 0.0,
      "with_address": 0,
      "distress_sources": [
        "foreclosure"
      ],
      "distress_count": 1,
      "hot_stack": false,
      "luc": "",
      "acres": "",
      "is_vacant_land": false,
      "is_vacant_home": false,
      "is_absentee": false,
      "is_out_of_state": false,
      "phones": [],
      "phone_types": [],
      "emails": [],
      "skip_trace_source": "",
      "parcel_id": "",
      "assessed_value": null,
      "estimated_value": null,
      "last_sale_price": null,
      "last_sale_year": null,
      "est_mortgage_balance": null,
      "est_equity": null,
      "est_arrears": null,
      "est_payoff": null,
      "subject_to_score": 25,
      "mortgage_signals": [
        "Active foreclosure"
      ]
    }
  ]
}